jsonstore.py
python_jsonstore-1.3.3.dist-info/licenses/LICENCE.md
python_jsonstore-1.3.3.dist-info/METADATA
python_jsonstore-1.3.3.dist-info/WHEEL
python_jsonstore-1.3.3.dist-info/top_level.txt
python_jsonstore-1.3.3.dist-info/RECORD
